simple_trade/__init__.py
simple_trade/compute_fibonacci_retracement.py
simple_trade/compute_indicators.py
simple_trade/compute_resistance_support.py
simple_trade/compute_trendlines.py
simple_trade/config.py
simple_trade/core.py
simple_trade/data.py
simple_trade/metrics.py
simple_trade/optimize_custom_strategies.py
simple_trade/optimize_premade_strategies.py
simple_trade/plot_ind.py
simple_trade/plot_test.py
simple_trade/run_band_trade_strategies.py
simple_trade/run_combined_trade_strategies.py
simple_trade/run_cross_trade_strategies.py
simple_trade/run_premade_strategies.py
simple_trade/momentum/__init__.py
simple_trade/momentum/awo.py
simple_trade/momentum/bop.py
simple_trade/momentum/cci.py
simple_trade/momentum/cmo.py
simple_trade/momentum/cog.py
simple_trade/momentum/crs.py
simple_trade/momentum/dpo.py
simple_trade/momentum/eri.py
simple_trade/momentum/fis.py
simple_trade/momentum/imi.py
simple_trade/momentum/kst.py
simple_trade/momentum/lsi.py
simple_trade/momentum/mac.py
simple_trade/momentum/msi.py
simple_trade/momentum/pgo.py
simple_trade/momentum/ppo.py
simple_trade/momentum/psy.py
simple_trade/momentum/qst.py
simple_trade/momentum/rmi.py
simple_trade/momentum/roc.py
simple_trade/momentum/rsi.py
simple_trade/momentum/rvg.py
simple_trade/momentum/sri.py
simple_trade/momentum/stc.py
simple_trade/momentum/sto.py
simple_trade/momentum/tsi.py
simple_trade/momentum/ttm.py
simple_trade/momentum/ult.py
simple_trade/momentum/vor.py
simple_trade/momentum/wad.py
simple_trade/momentum/wil.py
simple_trade/moving_average/__init__.py
simple_trade/moving_average/ads.py
simple_trade/moving_average/alm.py
simple_trade/moving_average/ama.py
simple_trade/moving_average/dem.py
simple_trade/moving_average/ema.py
simple_trade/moving_average/evw.py
simple_trade/moving_average/fma.py
simple_trade/moving_average/gma.py
simple_trade/moving_average/hma.py
simple_trade/moving_average/jma.py
simple_trade/moving_average/lsm.py
simple_trade/moving_average/mam.py
simple_trade-0.3.4.dist-info/licenses/LICENSE
simple_trade-0.3.4.dist-info/METADATA
simple_trade-0.3.4.dist-info/WHEEL
simple_trade-0.3.4.dist-info/top_level.txt
simple_trade-0.3.4.dist-info/RECORD
