Metadata-Version: 2.4
Name: simple_trade
Version: 0.3.4
Summary: Compute technical indicators and build trade strategies in a simple way
Author: Baris Soybilgen
License: AGPL-3.0
Project-URL: Source, https://github.com/BSoybilgen/simple-trade/
Keywords: algo,algorithmic,backtest,backtesting,candlestick,chart,crypto,currency,equity,exchange,finance,financial,forex,fx,indicator,invest,investing,investment,ohlc,ohlcv,order,price,profit,quant,quantitative,simulation,stocks,strategy,ticker,trader,trading
Classifier: Intended Audience :: Financial and Insurance Industry
Classifier: Intended Audience :: Science/Research
Classifier: License :: OSI Approved :: GNU Affero General Public License v3 or later (AGPLv3+)
Classifier: Operating System :: OS Independent
Classifier: Programming Language :: Python :: 3 :: Only
Classifier: Topic :: Office/Business :: Financial :: Investment
Classifier: Topic :: Scientific/Engineering :: Visualization
Requires-Python: >=3.10
License-File: LICENSE
Requires-Dist: yfinance>=0.2.59
Requires-Dist: pandas>=1.4.0
Requires-Dist: numpy>=1.22.0
Requires-Dist: joblib>=1.1.1
Requires-Dist: matplotlib>=3.6.0
Dynamic: author
Dynamic: classifier
Dynamic: description
Dynamic: description-content-type
Dynamic: keywords
Dynamic: license
Dynamic: license-file
Dynamic: project-url
Dynamic: requires-dist
Dynamic: requires-python
Dynamic: summary
